appium_rogue/__init__.py
appium_rogue/action.py
appium_rogue/atxdriver.py
appium_rogue/constant.py
appium_rogue/device.py
appium_rogue/driveragent.py
appium_rogue/environment.py
appium_rogue/exceptions.py
appium_rogue/flag.py
appium_rogue/locator.py
appium_rogue/log.py
appium_rogue/logcat.py
appium_rogue/powershell.py
appium_rogue/services.py
appium_rogue/shell.py
appium_rogue/uidumplib.py
appium_rogue/util.py
hulk/__init__.py
hulk/conn/__init__.py
hulk/conn/conn.py
hulk/datastore/__init__.py
hulk/datastore/datastore.py
hulk/datastore/factory.py
hulk/datastore/model.py
hulk/http/__init__.py
hulk/http/client.py
hulk/http/error.py
hulk/http/handle.py
hulk/http/helper.py
hulk/log/__init__.py
hulk/utils/__init__.py
hulk/utils/cipher.py
hulk/utils/decorators.py
hulk/utils/util.py
hulk/utils/xml2list.py
tests/__init__.py
tests/test_import.py
appium_rogue-0.0.5.dist-info/LICENSE
appium_rogue-0.0.5.dist-info/METADATA
appium_rogue-0.0.5.dist-info/WHEEL
appium_rogue-0.0.5.dist-info/top_level.txt
appium_rogue-0.0.5.dist-info/RECORD
