Metadata-Version: 2.1
Name: appium-rogue
Version: 0.0.5
Summary: App UI Test Framework
Home-page: https://git.wosai-inc.com/qa/appium-rogue
Author: Wosai QA Team
Author-email: shouqianba-test@shouqianba.com
License: MIT
Platform: UNKNOWN
Classifier: Development Status :: 5 - Production/Stable
Classifier: Environment :: Web Environment
Classifier: Intended Audience :: Developers
Classifier: License :: OSI Approved :: MIT License
Classifier: Programming Language :: Python :: 3 :: Only
Classifier: Topic :: Software Development :: Libraries :: Python Modules
Requires-Dist: aiohttp
Requires-Dist: Appium-Python-Client
Requires-Dist: termcolor
